raster_to_vector/__init__.py
raster_to_vector/computer_vision.py
raster_to_vector-0.0.1.dist-info/LICENSE
raster_to_vector-0.0.1.dist-info/METADATA
raster_to_vector-0.0.1.dist-info/WHEEL
raster_to_vector-0.0.1.dist-info/top_level.txt
raster_to_vector-0.0.1.dist-info/RECORD
