Metadata-Version: 2.1
Name: raster_to_vector
Version: 0.0.1
Summary: convert GIS WMTS tile image to polygon and point using computer vision
Home-page: https://github.com/billju/raster_to_vector
Author: chuboy
Author-email: billju666@gmail.com
Classifier: Programming Language :: Python :: 3
Classifier: License :: OSI Approved :: MIT License
Classifier: Operating System :: OS Independent
Requires-Python: >=3.8
License-File: LICENSE
Requires-Dist: rapidocr-onnxruntime
Requires-Dist: scikit-image
Requires-Dist: shapely
